fileexpect/FileBasedComparer.py
fileexpect/TextComparer.py
fileexpect/__init__.py
fileexpect-1.0.0.dist-info/LICENSE.txt
fileexpect-1.0.0.dist-info/WHEEL
fileexpect-1.0.0.dist-info/METADATA
fileexpect-1.0.0.dist-info/RECORD
