Metadata-Version: 2.1
Name: fileexpect
Version: 1.0.0
Summary: Tool to compare test results against file content
Home-page: https://github.com/francoistrahan/fileexpect
License: GPL-3.0
Author: François Trahan
Author-email: francois.trahan@gmail.com
Requires-Python: >=3.6,<4.0
Classifier: License :: OSI Approved :: GNU General Public License v3 (GPLv3)
Classifier: Programming Language :: Python :: 3
Classifier: Programming Language :: Python :: 3.6
Classifier: Programming Language :: Python :: 3.7
Project-URL: Repository, https://github.com/francoistrahan/fileexpect.git
